{
  "timestamp": "2026-02-22T07:31:00.100766",
  "cash": 117.68720910179718,
  "total_position_value": 9630.788302458688,
  "total_entry_value": 9774.02562560891,
  "total_unrealized_pnl": -143.23732315022153,
  "total_capital": 9748.475511560486,
  "confirmed_pnl": -284.1720832693814,
  "initial_capital": 10000.0,
  "total_pnl": -251.52448843951424,
  "positions": [
    {
      "symbol": "OGUSDT",
      "entry_price": 3.348,
      "current_price": 3.343,
      "quantity": 572.9246483193727,
      "entry_value": 1918.1517225732598,
      "current_value": 1915.287099331663,
      "unrealized_pnl": -2.864623241596746,
      "unrealized_pnl_pct": -0.14934289127836903,
      "entry_time": "2026-02-20T02:54:38.860263"
    },
    {
      "symbol": "FIDAUSDT",
      "entry_price": 0.0181,
      "current_price": 0.0172,
      "quantity": 107372.86852968454,
      "entry_value": 1943.4489203872902,
      "current_value": 1846.813338710574,
      "unrealized_pnl": -96.63558167671613,
      "unrealized_pnl_pct": -4.972375690607737,
      "entry_time": "2026-02-20T08:38:54.156406"
    },
    {
      "symbol": "RPLUSDT",
      "entry_price": 2.344,
      "current_price": 2.291,
      "quantity": 837.7686950072656,
      "entry_value": 1963.7298210970305,
      "current_value": 1919.3280802616455,
      "unrealized_pnl": -44.401740835385,
      "unrealized_pnl_pct": -2.2610921501706445,
      "entry_time": "2026-02-22T00:21:20.263096"
    },
    {
      "symbol": "APEUSDT",
      "entry_price": 0.1077,
      "current_price": 0.1073,
      "quantity": 18294.824462480854,
      "entry_value": 1970.3525946091881,
      "current_value": 1963.0346648241957,
      "unrealized_pnl": -7.31792978499243,
      "unrealized_pnl_pct": -0.37140204271123933,
      "entry_time": "2026-02-22T05:12:02.093050"
    },
    {
      "symbol": "HNTUSDT",
      "entry_price": 1.487,
      "current_price": 1.493,
      "quantity": 1330.4253980781045,
      "entry_value": 1978.3425669421415,
      "current_value": 1986.3251193306103,
      "unrealized_pnl": 7.9825523884687755,
      "unrealized_pnl_pct": 0.4034969737727042,
      "entry_time": "2026-02-22T07:24:48.076132"
    }
  ]
}